torchtools/__init__.py
torchtools/hooks.py
torchtools/utils.py
torch_print_summary-1.0.0.dist-info/METADATA
torch_print_summary-1.0.0.dist-info/WHEEL
torch_print_summary-1.0.0.dist-info/top_level.txt
torch_print_summary-1.0.0.dist-info/RECORD
