Metadata-Version: 2.1
Name: torch-print-summary
Version: 1.0.0
Summary: PyTorch Tools
Home-page: https://github.com/taoari/torchtools
Author: Tao Wei
Author-email: taowei@buffalo.edu
License: MIT
Platform: UNKNOWN
Classifier: License :: OSI Approved :: MIT License
Classifier: Programming Language :: Python :: 3
Classifier: Programming Language :: Python :: 3.7
